lnpi/__init__.py
lnpi/utilities/__init__.py
lnpi/utilities/box.py
lnpi/utilities/grid.py
lnpi/utilities/qualtrics.py
lnpi_utilities_michaeljsouder-0.0.1.dist-info/licenses/LICENSE
lnpi_utilities_michaeljsouder-0.0.1.dist-info/METADATA
lnpi_utilities_michaeljsouder-0.0.1.dist-info/WHEEL
lnpi_utilities_michaeljsouder-0.0.1.dist-info/top_level.txt
lnpi_utilities_michaeljsouder-0.0.1.dist-info/RECORD
