Metadata-Version: 2.4
Name: lnpi.utilities_michaeljsouder
Version: 0.0.1
Summary: A package for dealing with automation tasks in the lnpi lab/
Author-email: Michael Souder <michaeljsouder@gmail.com>
License-Expression: MIT
Project-URL: Homepage, https://github.umn.edu/soude017/lnpi.utilities
Classifier: Programming Language :: Python :: 3
Classifier: Operating System :: OS Independent
Requires-Python: >=3.10
License-File: LICENSE
Dynamic: license-file
